PulsarExcel.py
pulsar_excel-0.0.7.dist-info/LICENSE.txt
pulsar_excel-0.0.7.dist-info/METADATA
pulsar_excel-0.0.7.dist-info/WHEEL
pulsar_excel-0.0.7.dist-info/top_level.txt
pulsar_excel-0.0.7.dist-info/RECORD
