Metadata-Version: 2.1
Name: pulsar-excel
Version: 0.0.7
Summary: UNKNOWN
Home-page: https://github.com/Gyeongmin-lucid/pulsar-pip
Author: Gyeongmin Kim
Author-email: kgm1306@gmail.com
License: MIT
Keywords: pulsar
Platform: UNKNOWN
Requires-Dist: pandas
